[
{"name": "Butter bean & chorizo stew", "url": "https://www.bbcgoodfood.com/recipes/butter-bean-chorizo-stew", "ingredients": ["chorizo", "tomato", "butter beans", "pesto"]},
{"name": "Spanish rice & shrimp one-pot", "url": "https://www.bbcgoodfood.com/recipes/spanish-rice-shrimp-one-pot", "ingredients": ["onion", "pepper", "chorizo", "garlic", "olive oil", "basmati rice", "tomato", "shrimp"]},
{"name": "Tuna & sundried tomato pasta bake", "url": "https://www.bbcgoodfood.com/recipes/tuna-sundried-tomato-pasta-bake", "ingredients": ["rigatoni", "tomato", "thyme", "heavy cream", "tomato", "corn", "tuna", "cheddar", "parmesan"]},
{"name": "Easiest ever seafood rice", "url": "https://www.bbcgoodfood.com/recipes/easiest-ever-paella", "ingredients": ["olive oil", "leek", "chorizo", "turmeric", "rice", "chicken stock", "peas", "frozen seafood mix"]},
{"name": "Falafel burgers", "url": "https://www.bbcgoodfood.com/recipes/falafel-burgers-0", "ingredients": ["chickpeas", "red onion", "garlic", "parsley", "cumin", "coriander", "harissa paste", "all-purpose flour", "canola oil", "pita bread", "tomato salsa", "salad mix"]},
{"name": "Mustard-stuffed chicken", "url": "https://www.bbcgoodfood.com/recipes/mustard-stuffed-chicken", "ingredients": ["mozzarella", "cheddar", "whole grain mustard", "boneless chicken breast", "bacon"]},
{"name": "Green chicken salad", "url": "https://www.bbcgoodfood.com/recipes/green-chicken-salad", "ingredients": ["red onion", "lemon", "chicken", "celery", "scallions", "cucumber", "cornichons", "green pepper", "herbs", "sourdough", "natural yogurt", "dijon mustard", "mayonnaise", "olive oil"]},
{"name": "Nutty chicken curry", "url": "https://www.bbcgoodfood.com/recipes/nutty-chicken-curry", "ingredients": ["red chili", "ginger", "garlic", "coriander", "canola oil", "chicken breasts", "peanut butter", "chicken stock", "Greek yogurt"]},
{"name": "Fish tacos", "url": "https://www.bbcgoodfood.com/recipes/fish-tacos-2", "ingredients": ["cumin", "coriander", "paprika", "lime", "fish", "red cabbage", "tomato", "avocados", "vegetable oil", "soft tortillas", "coriander", "green chili", "sour cream", "chili sauce"]},
{"name": "Spiced spinach & potato pasty pies", "url": "https://www.bbcgoodfood.com/premium/spiced-spinach-potato-pasty-pies", "ingredients": ["canola oil", "cumin", "ginger", "garlic", "curry powder", "potato", "spinach", "garam masala", "egg", "turmeric", "pie crust", "all-purpose flour", "mango chutney"]},
{"name": "Crispy sesame lemon chicken", "url": "https://www.bbcgoodfood.com/recipes/crispy-sesame-lemon-chicken", "ingredients": ["chicken breast", "cornflour", "all-purpose flour", "baking powder", "pepper", "egg", "vegetable oil", "scallions", "noodles", "corn flour", "lemon", "honey", "soy sauce", "sesame seeds", "sesame oil"]},
{"name": "Cheese omelette", "url": "https://www.bbcgoodfood.com/recipes/cheese-omelette", "ingredients": ["egg", "olive oil", "butter", "cheddar"]},
{"name": "Spiced carrot & lentil soup", "url": "https://www.bbcgoodfood.com/recipes/spiced-carrot-lentil-soup", "ingredients": ["cumin", "chili flakes", "olive oil", "carrots", "red lentils", "vegetable stock", "milk", "plain yogurt"]},
{"name": "Asparagus & meatball orzo", "url": "https://www.bbcgoodfood.com/recipes/asparagus-meatball-orzo", "ingredients": ["meatballs", "orzo", "asparagus", "crème fraîche"]},
{"name": "shrimp & salmon burgers with spicy mayo", "url": "https://www.bbcgoodfood.com/recipes/shrimp-salmon-burgers-spicy-mayo", "ingredients": ["raw shrimp", "salmon", "scallions", "lemon", "coriander", "mayonnaise", "chili sauce", "lettuce", "cucumber", "olive oil", "hamburger buns"]},
{"name": "Crispy meatball pizza", "url": "https://www.bbcgoodfood.com/recipes/crispy-meatball-pizza", "ingredients": ["pizza dough", "all-purpose flour", "marinara sauce", "mozzarella", "meatballs", "oregano", "dill seeds", "chili flakes", "olive oil", "green olives", "salad mix"]},
{"name": "Raspberry ripple funfetti pancakes", "url": "https://www.bbcgoodfood.com/premium/raspberry-ripple-funfetti-pancakes", "ingredients": ["self-rising flour", "baking powder", "egg", "milk", "vanilla extract", "butter", "sprinkles", "raspberries", "sugar", "yogurt"]},
{"name": "Air fryer sausages", "url": "https://www.bbcgoodfood.com/recipes/air-fryer-sausages", "ingredients": ["sausage"]},
{"name": "Anytime pesto & shrimp pasta salad", "url": "https://www.bbcgoodfood.com/recipes/anytime-pesto-shrimp-pasta-salad", "ingredients": ["pasta", "green beans", "pesto", "crème fraîche", "cooked shrimp", "lemon", "pine nuts", "arugla"]},
{"name": "German-style cheese & bacon pancakes", "url": "https://www.bbcgoodfood.com/recipes/german-cheese-bacon-pancakes", "ingredients": ["bacon", "crème fraîche", "nutmeg", "dill seeds", "pancakes", "shallots", "gruyère", "cucumber", "white wine vinegar", "dill"]},
{"name": "Fastest ever lemon pudding", "url": "https://www.bbcgoodfood.com/recipes/fastest-ever-lemon-pudding", "ingredients": ["sugar", "butter", "self-rising flour", "egg", "lemon", "vanilla extract", "lemon curd", "crème fraîche"]},
{"name": "Air fryer baked potatoes", "url": "https://www.bbcgoodfood.com/recipes/air-fryer-baked-potatoes", "ingredients": ["potatoes", "canola oil", "cheddar", "sour cream", "bacon bits"]},
{"name": "Roasted lemony broccoli & mascarpone flatbreads", "url": "https://www.bbcgoodfood.com/premium/roasted-lemony-broccoli-mascarpone-flatbreads", "ingredients": ["flatbread", "peperonata", "broccoli", "lemon vinaigrette", "mascarpone", "red chili", "parmesan", "olive oil"]},
{"name": "Mushroom risotto", "url": "https://www.bbcgoodfood.com/recipes/mushroom-risotto", "ingredients": ["dried porcini", "vegetable stock", "olive oil", "onion", "garlic", "chestnut mushrooms", "risotto rice", "white wine", "butter", "parsley", "parmesan"]},
{"name": "Greek-style beans", "url": "https://www.bbcgoodfood.com/recipes/greek-style-beans", "ingredients": ["olive oil", "red onion", "garlic cloves", "oregano", "tomato purée", "tomato", "vegetable stock", "sugar", "butter beans", "lemon", "feta", "dill", "sourdough"]},
{"name": "Creamy ham, leek & mushroom spaghetti", "url": "https://www.bbcgoodfood.com/recipes/creamy-ham-leek-mushroom-spaghetti", "ingredients": ["olive oil", "leek", "chestnut mushrooms", "garlic", "spaghetti noodles", "ricotta cheese", "ham", "basil", "parmesan"]},
{"name": "Creamy courgette & bacon pasta", "url": "https://www.bbcgoodfood.com/recipes/creamy-courgette-bacon-pasta", "ingredients": ["olive oil", "pancetta", "zucchini", "garlic", "parmesan", "crème fraîche", "tagliatelle noodles"]},
{"name": "Microwave sweet & sour chicken", "url": "https://www.bbcgoodfood.com/recipes/easy-sweet-sour-chicken", "ingredients": ["ketchup", "malt vinegar", "dark brown sugar", "garlic", "chicken breast", "onion", "red peppers", "pineapple", "sugar snap peas", "cashew nuts"]},
{"name": "Mushroom & potato curry", "url": "https://www.bbcgoodfood.com/recipes/one-pot-mushroom-potato-curry", "ingredients": ["vegetable oil", "onion", "potato", "eggplant", "button mushrooms", "curry paste", "vegetable stock", "coconut milk", "coriander"]},
{"name": "Bang bang chicken & vegetable noodles", "url": "https://www.bbcgoodfood.com/recipes/bang-bang-chicken-vegetable-noodles", "ingredients": ["chicken breast", "zucchini", "carrots", "scallions", "beansprouts", "soybeans", "peanut butter", "soy sauce", "sweet chili sauce", "sesame oil", "lime", "peanuts", "red chili"]},
{"name": "Super-quick fish curry", "url": "https://www.bbcgoodfood.com/recipes/super-quick-fish-curry", "ingredients": ["vegetable oil", "onion", "garlic", "curry paste", "tomato", "vegetable stock", "fish", "rice"]},
{"name": "Hoisin mackerel pancakes", "url": "https://www.bbcgoodfood.com/recipes/hoisin-mackerel-pancakes", "ingredients": ["fish", "hoisin sauce", "scallions", "cucumber", "lettuce", "vegetable oil", "Chinese pancakes"]},
{"name": "Summer-in-winter chicken", "url": "https://www.bbcgoodfood.com/recipes/summer-winter-chicken", "ingredients": ["olive oil", "chicken breasts", "cherry tomato", "pesto", "crème fraîche", "basil"]},
{"name": "Creamy linguine with ham, lemon & basil", "url": "https://www.bbcgoodfood.com/recipes/creamy-linguine-ham-lemon-basil", "ingredients": ["linguine", "prosciutto", "olive oil", "lemon", "egg", "crème fraîche", "basil", "parmesan"]},
{"name": "Help-yourself tuna rice salad", "url": "https://www.bbcgoodfood.com/recipes/help-yourself-tuna-rice-salad", "ingredients": ["rice", "tuna", "peas", "red peppers", "tomato", "scallions", "parsley", "green olives", "mayonnaise", "lemon", "olive oil"]},
{"name": "Salmon, broccoli & potato bake", "url": "https://www.bbcgoodfood.com/recipes/salmon-broccoli-potato-bake", "ingredients": ["potato", "broccoli", "crème fraîche", "whole grain mustard", "salmon", "parmesan"]},
{"name": "Build your own pesto pasta salad", "url": "https://www.bbcgoodfood.com/recipes/build-your-own-pesto-pasta-salad", "ingredients": ["bow-tie pasta", "olive oil", "pine nuts", "pesto", "basil", "lemon", "parmesan", "cherry tomato"]},
{"name": "Quick chicken chasseur", "url": "https://www.bbcgoodfood.com/recipes/quick-chicken-chasseur", "ingredients": ["bacon", "chicken breast", "button mushrooms", "all-purpose flour", "tomato", "beef stock cube", "Worcestershire sauce", "parsley"]},
{"name": "One-pan chicken couscous", "url": "https://www.bbcgoodfood.com/recipes/one-pan-chicken-couscous", "ingredients": ["olive oil", "onion", "chicken breast", "ginger", "harissa paste", "dried apricots", "chickpeas", "couscous", "chicken stock", "coriander"]},
{"name": "Spring meatball soup", "url": "https://www.bbcgoodfood.com/recipes/spring-meatball-soup", "ingredients": ["olive oil", "carrots", "white beans", "chicken stock", "meatballs", "tomato sauce", "peas", "spinach & ricotta tortellini", "spinach", "lemon", "dill", "garlic bread"]},
{"name": "Chicken fried rice", "url": "https://www.bbcgoodfood.com/recipes/chicken-sweetcorn-egg-fried-rice", "ingredients": ["canola oil", "egg", "stir-fry vegetables", "curry powder", "sweetcorn", "cooked rice", "chicken breast", "soy sauce", "sweet chili sauce", "ketchup"]},
{"name": "Chickpea & coriander burgers", "url": "https://www.bbcgoodfood.com/recipes/chickpea-coriander-burgers", "ingredients": ["chickpeas", "lemon", "cumin", "coriander", "egg", "breadcrumbs", "red onion", "olive oil", "Hawaiian rolls", "tomato"]},
{"name": "Quick lamb biryani", "url": "https://www.bbcgoodfood.com/recipes/quick-lamb-biryani", "ingredients": ["curry paste", "lamb", "basmati rice", "chicken stock", "spinach"]},
{"name": "Italian stuffed chicken", "url": "https://www.bbcgoodfood.com/recipes/italian-stuffed-chicken", "ingredients": ["olives", "garlic", "herbs", "ricotta cheese", "chicken breasts", "tomato", "olive oil"]},
{"name": "Secret green sauce spaghetti", "url": "https://www.bbcgoodfood.com/recipes/secret-green-sauce-spaghetti", "ingredients": ["spaghetti", "baby spinach", "peas", "basil", "pesto", "half and half", "parmesan"]},
{"name": "Vegetarian quesadillas", "url": "https://www.bbcgoodfood.com/recipes/cheesy-bean-chipotle-quesadillas", "ingredients": ["mixed beans", "chipotle pepper", "coriander", "cheddar", "soft tortillas"]},
{"name": "Crispy sea bass with brown butter pilaf, seedy gremolata & slaw", "url": "https://www.bbcgoodfood.com/premium/crispy-sea-bass-with-brown-butter-pilaf-seedy-gremolata-slaw", "ingredients": ["corn flour", " cayenne pepper", "garlic", "canola oil", "sea bass", "brown butter pilaf", "cabbage & corn slaw", "tahini dressing"]},
{"name": "Southern-fried chicken tacos", "url": "https://www.bbcgoodfood.com/recipes/southern-fried-chicken-tacos", "ingredients": ["chicken strips", "chives", "sour cream", "soft tortillas", "lettuce", "scallions", "hot sauce"]},
{"name": "Vegetarian fajitas", "url": "https://www.bbcgoodfood.com/recipes/veggie-fajitas", "ingredients": ["black beans", "coriander", "soft tortillas", "avocado", "sour cream", "yellow pepper", "vegetable oil", "red onion", "garlic", "chili powder", "paprika", "cumin", "lime"]},
{"name": "Tomato & pasta soup", "url": "https://www.bbcgoodfood.com/recipes/orzo-tomato-soup", "ingredients": ["olive oil", "onion", "celery sticks", "garlic", "tomato purée", "tomato", "chickpeas", "orzo", "vegetable stock", "pesto", "garlic bread"]},
{"name": "Pork & apple burgers", "url": "https://www.bbcgoodfood.com/recipes/pork-apple-burgers", "ingredients": ["ground pork", "hamburger buns", "onion marmalade", "apples", "arugala", "mayonnaise", "English mustard", "sweet potato"]},
{"name": "Carbonara with chicken", "url": "https://www.bbcgoodfood.com/recipes/carbonara-chicken", "ingredients": ["spaghetti", "olive oil", "garlic", "pancetta", "chicken breast", "egg", "Grana Padano", "butter"]},
{"name": "Potato, pea & egg curry rotis", "url": "https://www.bbcgoodfood.com/recipes/potato-pea-egg-curry-rotis", "ingredients": ["vegetable oil", "curry paste", "tomato", "potato", "peas", "egg", "rotis", "yogurt"]},
{"name": "Chicken & veg bowl", "url": "https://www.bbcgoodfood.com/recipes/chicken-veg-bowl", "ingredients": ["basmati rice", "rapeseed oil", "garlic clove", "chicken", "hoisin sauce", "frozen edamame beans", "frozen sweetcorn", "grated carrots", "red peppers", "avocado", "lemon"]},
{"name": "Simple stir-fry", "url": "https://www.bbcgoodfood.com/recipes/simple-stir-fry", "ingredients": ["vegetables", "rapeseed oil", "garlic clove", "ginger", "reduced salt soy sauce", "sweet chili sauce", "cooked shrimp", "egg noodles"]},
{"name": "Chicken goujons", "url": "https://www.bbcgoodfood.com/recipes/crispy-chicken-strips", "ingredients": ["buttermilk", "large  chicken", "panko breadcrumbs", "vegetable oil", "ketchup", "soy sauce", "white wine vinegar", "carrots", "lemon", "olive oil", "potato"]},
{"name": "Teriyaki salmon & green beans", "url": "https://www.bbcgoodfood.com/recipes/teriyaki-salmon-green-beans", "ingredients": ["salmon", "green beans", "lemon", "soy sauce", "honey", "mirin", "garlic", "noodles"]},
{"name": "Swedish meatball burgers", "url": "https://www.bbcgoodfood.com/recipes/swedish-meatball-burgers", "ingredients": ["ground beef", "onion", "egg", "breadcrumbs", "nutmeg", "garlic powder", "hamburger buns"]},
{"name": "15-minute chicken & halloumi burgers", "url": "https://www.bbcgoodfood.com/recipes/15-minute-chicken-halloumi-burgers", "ingredients": ["chicken breast", "vegetable oil", "piri-piri sauce", "lemon", "hamburger buns", "halloumi", "cabbage", "mayonnaise", "hummus", "arugal", "red peppers"]},
{"name": "Honey, sesame & orange king shrimp", "url": "https://www.bbcgoodfood.com/recipes/honey-sesame-orange-king-shrimp", "ingredients": ["sesame oil", "orange", "honey", "soy sauce", "rice vinegar", "corn flour", "sesame seeds", "Chinese five-spice powder", "shrimp", "vegetable oil", "garlic", "scallions", "long-grain rice"]},
{"name": "Easy Singapore noodles (chow mein)", "url": "https://www.bbcgoodfood.com/recipes/singapore-noodles", "ingredients": ["vermicelli noodles", "curry powder", "turmeric", "sugar", "sesame oil", "soy sauce", "vegetable oil", "onion", "pepper", "beansprouts", "red chili"]},
{"name": "Gnocchi fish pie", "url": "https://www.bbcgoodfood.com/recipes/gnocchi-fish-pie", "ingredients": ["gnocchi", "skim milk", "corn flour", "fish", "scallions", "chives", "crème fraîche", "capers", "peas", "olive oil", "broccoli"]},
{"name": "Easy egg fried rice", "url": "https://www.bbcgoodfood.com/recipes/oriental-egg-fried-rice", "ingredients": ["long grain rice", "peas", "canola oil", "bacon", "red pepper", "garlic", "egg", "Chinese five-spice powder", "scallions"]},
{"name": "Spaghetti aglio e olio with crispy bacon", "url": "https://www.bbcgoodfood.com/recipes/spaghetti-aglio-e-olio-with-crispy-bacon", "ingredients": ["olive oil", "bacon", "spaghetti noodles", "garlic", "parsley"]},
{"name": "One-pan pork stroganoff", "url": "https://www.bbcgoodfood.com/premium/one-pan-pork-stroganoff", "ingredients": ["chestnut mushrooms", "olive oil", "onion", "paprika", "pork tenderloin", "heavy cream", "soy sauce", "mashed potatoes"]},
{"name": "Cheesy ham & broccoli pasta", "url": "https://www.bbcgoodfood.com/recipes/cheesy-ham-broccoli-pasta", "ingredients": ["pasta", "broccoli", "vegetable oil", "onion", "garlic", "ham", "heavy cream", "English mustard", "cheddar"]},
{"name": "Blackened salmon fajitas", "url": "https://www.bbcgoodfood.com/recipes/blackened-salmon-fajitas", "ingredients": ["salmon", "canola oil", "fajita kit", "avocados", "lime"]},
{"name": "Salmon egg-fried rice", "url": "https://www.bbcgoodfood.com/recipes/salmon-egg-fried-rice", "ingredients": ["ginger", "garlic", "soy sauce", "rice wine", "vegetable oil", "carrot", "corn", "salmon", "basmati rice", "egg", "hot sauce"]},
{"name": "Pasta with salmon & peas", "url": "https://www.bbcgoodfood.com/recipes/pasta-salmon-peas", "ingredients": ["fusilli noodles", "butter", "shallot", "peas", " salmon", "crème fraîche", "vegetable stock cube", "chives"]},
{"name": "Vegetarian carbonara", "url": "https://www.bbcgoodfood.com/recipes/healthier-veggie-carbonara", "ingredients": ["zucchini", "spaghetti noodles", "egg", "vegan parmesan-style cheese", "olive oil", "lemon", "thyme", "chestnut mushrooms", "garlic", "parsley", "lemon"]},
{"name": "Speedy sausage stroganoff tagliatelle", "url": "https://www.bbcgoodfood.com/recipes/speedy-sausage-stroganoff-tagliatelle", "ingredients": ["unsalted butter", "olive oil", "pork sausage", "chestnut mushrooms", "paprika", "sour cream", "whole grain mustard", "beef stock", "tagliatelle", "parsley"]},
{"name": "Smoked pea carbonara", "url": "https://www.bbcgoodfood.com/premium/smoked-pea-carbonara", "ingredients": ["peas", "spaghetti noodles", "extra-firm tofu", "corn flour", "paprika", "olive oil", "garlic", "parmesan-style vegan cheese", "silken tofu", "oat milk", "dijon mustard", "lemon", "yeast", "white miso paste", "pepper"]},
{"name": "Veggie hummus pasta salad", "url": "https://www.bbcgoodfood.com/recipes/veggie-hummus-pasta-salad", "ingredients": ["chickpeas", "tahini", "olive oil", "garlic", "lemon", "pasta", "baby spinach", "cherry tomato", "cucumber", "olives"]},
{"name": "Tofu stir-fry", "url": "https://www.bbcgoodfood.com/recipes/tofu-stir-fry", "ingredients": ["soy sauce", "honey", "white wine vinegar", "tofu", "canola oil", "garlic", "ginger", "carrots", "broccoli", "red pepper", "corn flour", "spring onion", "sesame seeds", "coriander"]},
{"name": "Coconut fish curry & rice", "url": "https://www.bbcgoodfood.com/recipes/coconut-fish-curry-rice", "ingredients": ["fish", "lime", "turmeric", "vegetable oil", "onion", "ginger", "garlic", "cumin", "coriander", "chili flakes", "tomato purée", "butternut squash", "sweet potato", "coconut milk", "tamarind paste", "coriander", "rice"]},
{"name": "Beef rissoles", "url": "https://www.bbcgoodfood.com/recipes/beef-rissoles", "ingredients": ["onion", "breadcrumbs", "ground beef", "zucchini", "carrot", "egg", "garlic", "herbs", "Worcestershire sauce", "vegetable oil"]},
{"name": "Tomato sauce for pasta", "url": "https://www.bbcgoodfood.com/recipes/tomato-basil-sauce", "ingredients": ["olive oil", "garlic", "tomato", "vegetable stock", "tomato purée", "basil"]},
{"name": "Fridge-raid fried rice", "url": "https://www.bbcgoodfood.com/recipes/fridge-raid-fried-rice", "ingredients": ["vegetable oil", "onion", "carrot", "green beans", "yellow pepper", "broccoli", "chicken", "rice", "egg", "sesame oil", "oyster sauce", "scallions", "sesame seeds"]},
{"name": "Hob-to-table moussaka", "url": "https://www.bbcgoodfood.com/recipes/hob-table-moussaka", "ingredients": ["olive oil", "onion", "garlic", "ground lamb", "plum tomato", "tomato purée", "cinnamon", "eggplant", "feta cheese", "mint"]},
{"name": "Peanut butter noodles with tofu & veg", "url": "https://www.bbcgoodfood.com/recipes/peanut-butter-noodles-with-tofu-veg", "ingredients": ["edamame beans", "sesame oil", "garlic", "green beans", "kale", "firm tofu", "whole-grain", "scallions", "sesame seeds", "peanut butter", "tahini", "soy sauce"]},
{"name": "Broccoli & green beans with toasted hazelnut butter", "url": "https://www.bbcgoodfood.com/recipes/broccoli-green-beans-toasted-hazelnut-butter", "ingredients": ["green beans", "broccoli", "hazelnut", "butter"]},
{"name": "Spicy sausage & bean one-pot", "url": "https://www.bbcgoodfood.com/recipes/spicy-sausage-bean-one-pot", "ingredients": ["vegetable oil", "onion", "Cumberland sausage", "garlic", "kidney beans", "parsley"]},
{"name": "Halloumi with bulgur, chickpea & rocket salad", "url": "https://www.bbcgoodfood.com/recipes/halloumi-bulghar-chickpea-rocket-salad", "ingredients": ["wheat", "halloumi", "olive oil", "lime", "paprika", "chickpea", "arugala"]},
{"name": "Sausage, leek & fennel pasta", "url": "https://www.bbcgoodfood.com/recipes/sausage-leek-fennel-pasta", "ingredients": ["olive oil", "pork sausage", "leek", "fusilli noodles", "garlic", "dill seeds", "whole grain mustard", "lemon", "parmesan"]},
{"name": "Salmon fish finger sandwich", "url": "https://www.bbcgoodfood.com/recipes/salmon-fish-finger-sandwich", "ingredients": ["all-purpose flour", "egg", "breadcrumbs", "salmon", "vegetable oil", "lettuce", "sub rolls", "mayonnaise", "capers", "scallions", "tarragon", "lemon"]},
{"name": "Thai shrimp noodles", "url": "https://www.bbcgoodfood.com/recipes/thai-shrimp-noodles", "ingredients": ["egg noodles", "vegetable oil", "ginger", "garlic", "red chilis", "peas", "shrimp", "egg", "soy sauce", "lime", "scallions", "coriander"]},
{"name": "Spring onion, pea & pancetta tart", "url": "https://www.bbcgoodfood.com/premium/spring-onion-pea-pancetta-tart", "ingredients": ["puff pastry", "scallions", "olive oil", "pancetta", "soft cheese", "basil", "egg", "parmesan", "dijon mustard", "peas"]},
{"name": "Spicy black bean tacos", "url": "https://www.bbcgoodfood.com/recipes/spicy-black-bean-tacos", "ingredients": ["vegetable oil", "garlic", "black beans", "cider vinegar", "honey", "paprika", "cumin", "garlic", "coriander", "green chili", "avocados", "lime", "pomegranate seeds", "green chili", "onion", "coriander", "soft tortillas", "chipotle pepper", "sour cream"]},
{"name": "John's chicken nacho one-pot", "url": "https://www.bbcgoodfood.com/recipes/johns-chicken-one-pot", "ingredients": ["olive oil", "chorizo", "paprika", "cherry tomato", "chicken breast", "tortilla chips", "crème fraîche", "jalapeño pepper", "crème fraîche", "avocado"]},
{"name": "Quick & easy Korean pork", "url": "https://www.bbcgoodfood.com/recipes/quick-easy-korean-pork", "ingredients": ["pork belly", "lettuce", "pear", "white  onion", "garlic", "ginger", "scallions", "soy sauce", "brown sugar", "sesame oil", "Korean chili paste", "Korean soy bean paste", "Korean chili paste", "mirin", "sesame seed"]},
{"name": "Baked cod with creamy mushroom & leek orzo", "url": "https://www.bbcgoodfood.com/recipes/baked-cod-with-creamy-mushroom-leek-orzo", "ingredients": ["all-purpose flour", "fish", "olive oil", "lemon", "thyme", "leek", "mushrooms", "orzo", "stock", "crème fraîche"]},
{"name": "Gnocchi with roasted red pepper sauce", "url": "https://www.bbcgoodfood.com/recipes/gnocchi-roasted-red-pepper-sauce", "ingredients": ["gnocchi", "pepper sauce", "mozzarella", "breadcrumbs"]},
{"name": "Air fryer chicken thighs", "url": "https://www.bbcgoodfood.com/recipes/air-fryer-chicken-thighs", "ingredients": ["paprika", "herbs", "garlic", "chicken thigh", "olive oil"]},
{"name": "Lamb meatballs & green tahini tabbouleh", "url": "https://www.bbcgoodfood.com/recipes/lamb-meatballs-green-tahini-tabbouleh", "ingredients": ["tahini", "yogurt", "parsley", "lemon", "garlic", "vegetable oil", "meatballs", "mixed grains", "beetroot", "scallions", "baby tomato", "black olives", "cucumber", "za’atar"]},
{"name": "Honey chicken", "url": "https://www.bbcgoodfood.com/recipes/honey-chicken", "ingredients": ["chicken breasts", "all-purpose flour", "ginger", "garlic cloves", "soy sauce", "honey", "lemon", "vegetable oil", "rice", "broccoli"]},
{"name": "Easy teriyaki chicken", "url": "https://www.bbcgoodfood.com/recipes/easy-teriyaki-chicken", "ingredients": ["sesame oil", "chicken thighs", "garlic", "ginger", "honey", "soy sauce", "rice wine vinegar", "sesame seeds", "scallions", "rice", "bok choy"]},
{"name": "Easy Thai shrimp curry", "url": "https://www.bbcgoodfood.com/recipes/easy-thai-shrimp-curry", "ingredients": ["vegetable oil", "onion", "ginger", "Thai red curry paste", "tomato", "coconut cream", "shrimp", "coriander"]},
{"name": "Creamy chicken pasta", "url": "https://www.bbcgoodfood.com/recipes/creamy-chicken-pasta", "ingredients": ["penne noodles", "olive oil", "garlic", "baby spinach", "soft cheese", "parmesan", "chicken breast", "peas", "parsley"]},
{"name": "Smash burgers", "url": "https://www.bbcgoodfood.com/recipes/smash-burgers", "ingredients": ["hamburger buns", "canola oil", "ground beef", "cheddar", "red onion", "lettuce", "tomato", "gherkin", "mayonnaise"]},
{"name": "Air-fryer fish fingers", "url": "https://www.bbcgoodfood.com/recipes/air-fryer-fish-fingers", "ingredients": ["fish", "egg", "breadcrumbs", "white bread"]},
{"name": "Air fryer pork chops", "url": "https://www.bbcgoodfood.com/recipes/air-fryer-pork-chops", "ingredients": ["pork chops", "vegetable oil", "oregano", "paprika", "mustard powder", "onion powder", "parmesan", "greens", "peas"]},
{"name": "Air fryer meatballs", "url": "https://www.bbcgoodfood.com/recipes/air-fryer-meatballs", "ingredients": ["sausage", "ground beef", "onion", "parmesan", "breadcrumbs", "parsley", "egg"]},
{"name": "Quick pizza dough", "url": "https://www.bbcgoodfood.com/recipes/quick-pizza-dough-2", "ingredients": ["bread flour", "yeast", "sugar", "pizza toppings"]}
]